handsome/__init__.py
handsome/boy/__init__.py
handsome/boy/information.py
handsome/boy/message.py
our_love-0.1.dist-info/LICENSE
our_love-0.1.dist-info/LICENSE.txt
our_love-0.1.dist-info/METADATA
our_love-0.1.dist-info/WHEEL
our_love-0.1.dist-info/top_level.txt
our_love-0.1.dist-info/RECORD
