Metadata-Version: 2.1
Name: our-love
Version: 0.1
Summary: The members of our team are 林沐阳 and 梁舒葶!
Home-page: UNKNOWN
Author: lmy+lst
Author-email: UNKNOWN
License: UNKNOWN
Platform: UNKNOWN
